platonic_io/GUI.py
platonic_io/__init__.py
platonic_io/cli.py
platonic_io/get_plate.py
platonic_io/integration_test.py
platonic_io/local_utils.py
platonic_io/models/License_character_recognition_weight.h5
platonic_io/models/MobileNets_character_recognition.json
platonic_io/models/license_character_classes.npy
platonic_io/models/wpod-net.h5
platonic_io/models/wpod-net.json
platonic_io/ocr.py
platonic_io/platonic_io2.py
platonic_io/recognition_engine.py
platonic_io-0.4.1.dist-info/entry_points.txt
platonic_io-0.4.1.dist-info/LICENSE
platonic_io-0.4.1.dist-info/WHEEL
platonic_io-0.4.1.dist-info/METADATA
platonic_io-0.4.1.dist-info/RECORD
